{
  "entityType" : "DEVICE",
  "entity" : {
    "additionalInfo" : {
      "lastConnectedGateway" : "68492a60-afcc-11f0-94c3-f75567048948"
    },
    "customerId" : {
      "entityType" : "CUSTOMER",
      "id" : "f2559730-0589-11f1-abf4-490de52379ba"
    },
    "deviceData" : {
      "configuration" : {
        "type" : "DEFAULT"
      },
      "transportConfiguration" : {
        "type" : "DEFAULT"
      }
    },
    "deviceProfileId" : {
      "entityType" : "DEVICE_PROFILE",
      "id" : "faf9af4e-9eb2-11f0-96c2-df048c90c8a5"
    },
    "externalId" : {
      "entityType" : "DEVICE",
      "id" : "fb29e703-9eb2-11f0-96c2-df048c90c8a5"
    },
    "firmwareId" : null,
    "id" : {
      "entityType" : "DEVICE",
      "id" : "fb29e703-9eb2-11f0-96c2-df048c90c8a5"
    },
    "label" : "Comp-9",
    "name" : "Comp-9",
    "softwareId" : null,
    "type" : "Electricity meter"
  },
  "credentials" : {
    "credentialsId" : "oOPkuzY7tyQpY2sbk5FT",
    "credentialsType" : "ACCESS_TOKEN",
    "credentialsValue" : null
  },
  "relations" : [ {
    "additionalInfo" : null,
    "from" : {
      "entityType" : "DEVICE",
      "id" : "fb29e703-9eb2-11f0-96c2-df048c90c8a5"
    },
    "to" : {
      "entityType" : "DEVICE",
      "id" : "fb41b4c0-9eb2-11f0-96c2-df048c90c8a5"
    },
    "type" : "Contains",
    "typeGroup" : "COMMON",
    "version" : 2788
  } ],
  "attributes" : {
    "SERVER_SCOPE" : [ {
      "booleanValue" : null,
      "doubleValue" : null,
      "jsonValue" : null,
      "key" : "Block No.",
      "lastUpdateTs" : 1759315200384,
      "longValue" : 23,
      "strValue" : null
    }, {
      "booleanValue" : null,
      "doubleValue" : null,
      "jsonValue" : null,
      "key" : "DLU",
      "lastUpdateTs" : 1759315200384,
      "longValue" : null,
      "strValue" : "4:DLL1_inst"
    }, {
      "booleanValue" : null,
      "doubleValue" : null,
      "jsonValue" : null,
      "key" : "FACI",
      "lastUpdateTs" : 1759315200384,
      "longValue" : null,
      "strValue" : "Air compressor No.9"
    }, {
      "booleanValue" : null,
      "doubleValue" : null,
      "jsonValue" : null,
      "key" : "PRPS",
      "lastUpdateTs" : 1759315200384,
      "longValue" : null,
      "strValue" : "MNT"
    }, {
      "booleanValue" : null,
      "doubleValue" : null,
      "jsonValue" : null,
      "key" : "SECT",
      "lastUpdateTs" : 1759315200384,
      "longValue" : null,
      "strValue" : "MNT"
    }, {
      "booleanValue" : false,
      "doubleValue" : null,
      "jsonValue" : null,
      "key" : "active",
      "lastUpdateTs" : 1769077943115,
      "longValue" : null,
      "strValue" : null
    }, {
      "booleanValue" : null,
      "doubleValue" : null,
      "jsonValue" : null,
      "key" : "capcha",
      "lastUpdateTs" : 1759315200384,
      "longValue" : null,
      "strValue" : "COMPRESSOR No.3"
    }, {
      "booleanValue" : null,
      "doubleValue" : null,
      "jsonValue" : null,
      "key" : "inactivityAlarmTime",
      "lastUpdateTs" : 1769077943077,
      "longValue" : 1769077943076,
      "strValue" : null
    }, {
      "booleanValue" : null,
      "doubleValue" : 21396.14599999995,
      "jsonValue" : null,
      "key" : "kWh_month",
      "lastUpdateTs" : 1769076600255,
      "longValue" : null,
      "strValue" : null
    }, {
      "booleanValue" : null,
      "doubleValue" : 432.8279999999795,
      "jsonValue" : null,
      "key" : "kWh_today",
      "lastUpdateTs" : 1769076600255,
      "longValue" : null,
      "strValue" : null
    }, {
      "booleanValue" : null,
      "doubleValue" : 3419.932999999961,
      "jsonValue" : null,
      "key" : "kWh_week",
      "lastUpdateTs" : 1769076600255,
      "longValue" : null,
      "strValue" : null
    }, {
      "booleanValue" : null,
      "doubleValue" : 21396.14599999995,
      "jsonValue" : null,
      "key" : "kWh_year",
      "lastUpdateTs" : 1769076600255,
      "longValue" : null,
      "strValue" : null
    }, {
      "booleanValue" : null,
      "doubleValue" : null,
      "jsonValue" : null,
      "key" : "lastActivityTime",
      "lastUpdateTs" : 1769077323198,
      "longValue" : 1769077320195,
      "strValue" : null
    }, {
      "booleanValue" : null,
      "doubleValue" : null,
      "jsonValue" : null,
      "key" : "lastConnectTime",
      "lastUpdateTs" : 1769076719461,
      "longValue" : 1769076719461,
      "strValue" : null
    }, {
      "booleanValue" : null,
      "doubleValue" : null,
      "jsonValue" : null,
      "key" : "lastDisconnectTime",
      "lastUpdateTs" : 1769077320204,
      "longValue" : 1769077320204,
      "strValue" : null
    }, {
      "booleanValue" : null,
      "doubleValue" : null,
      "jsonValue" : null,
      "key" : "xPos",
      "lastUpdateTs" : 1761539299604,
      "longValue" : null,
      "strValue" : "0.35011888913740924"
    }, {
      "booleanValue" : null,
      "doubleValue" : null,
      "jsonValue" : null,
      "key" : "yPos",
      "lastUpdateTs" : 1761539299604,
      "longValue" : null,
      "strValue" : "0.11839360327697425"
    } ],
    "SHARED_SCOPE" : [ ]
  },
  "calculatedFields" : [ ]
}